pykinetic/__init__.py
pykinetic/classes.py
pykinetic/userinput.py
pykinetic/utils.py
pykinetic/scripts/pykinetic-model.py
pykinetic/scripts/pykinetic-scan.py
pykinetic/templates/cplusplus_header.default
pykinetic/templates/cplusplus_tail.default
pykinetic/templates/cplusplus_tail.rk45adapt
pykinetic/templates/cplusplus_tail.rk45const
pykinetic/templates/python_PFR.head
pykinetic/templates/python_PFR.tail
pykinetic/templates/python_batch.head
pykinetic/templates/python_batch.tail
pykinetic/templates/python_semibatch.head
pykinetic/templates/python_semibatch.tail
pykinetic/templates/python_semibatch_extended.head
pykinetic/templates/python_semibatch_extended.tail
pykinetic/tests/__init__.py
pykinetic/tests/testclasses.py
pykinetic/tests/testuserinput.py
pykinetic/tests/testwriters.py
pykinetic/writers/__init__.py
pykinetic/writers/_base.py
pykinetic/writers/cplusplus.py
pykinetic/writers/python.py
pykinetic-0.1.0.data/scripts/pykinetic-model.py
pykinetic-0.1.0.data/scripts/pykinetic-scan.py
pykinetic-0.1.0.dist-info/LICENSE
pykinetic-0.1.0.dist-info/METADATA
pykinetic-0.1.0.dist-info/WHEEL
pykinetic-0.1.0.dist-info/top_level.txt
pykinetic-0.1.0.dist-info/RECORD
