Metadata-Version: 2.1
Name: pykinetic
Version: 0.1.0
Summary: A python library and command line apps to write microkinetic models for chemistry
Home-page: https://github.com/rperezsoto/pykinetic
Author: Raúl Pérez-Soto
Author-email: Raúl Pérez-Soto <rperezsoto.research@gmail.com>, Sergio Pablo-García <spgarcica@gmail.com>
Project-URL: Homepage, https://github.com/rperezsoto/pykinetic
Project-URL: Docs, https://rperezsoto.github.io/pykinetic/
Keywords: compchem,microkinetics
Classifier: Programming Language :: Python :: 3
Classifier: License :: OSI Approved :: MIT License
Classifier: Operating System :: OS Independent
Requires-Python: >=3.6
License-File: LICENSE
Requires-Dist: setuptools
Requires-Dist: pathlib
Requires-Dist: numpy
